cwt_seismology/__init__.py
cwt_seismology/wavelet.py
cwt_seismology/utils/__init__.py
cwt_seismology/utils/obspy_utils.py
cwt_seismology-0.0.2.dist-info/LICENSE
cwt_seismology-0.0.2.dist-info/METADATA
cwt_seismology-0.0.2.dist-info/WHEEL
cwt_seismology-0.0.2.dist-info/top_level.txt
cwt_seismology-0.0.2.dist-info/RECORD
