Metadata-Version: 2.1
Name: cwt-seismology
Version: 0.0.2
Summary: Wavelet transform for seismic signal detection.
Home-page: https://github.com/rcabdia/CWT
Author: rcabdia
Author-email: rcabdia@roa.es
License: UNKNOWN
Platform: UNKNOWN
Classifier: Programming Language :: Python :: 3
Classifier: License :: OSI Approved :: GNU Library or Lesser General Public License (LGPL)
Classifier: Operating System :: OS Independent
Requires-Python: >=3.6
Requires-Dist: numpy
Requires-Dist: scipy (>=1.4.0)
Requires-Dist: obspy
